grokking/__init__.py
grokking/_modidx.py
grokking/helpers.py
grokking/setup.py
grokking/transformers.py
grokking-0.0.7.dist-info/LICENSE
grokking-0.0.7.dist-info/METADATA
grokking-0.0.7.dist-info/WHEEL
grokking-0.0.7.dist-info/entry_points.txt
grokking-0.0.7.dist-info/top_level.txt
grokking-0.0.7.dist-info/RECORD
